spoty/__init__.py
spoty/audio_files.py
spoty/cli.py
spoty/csv_playlist.py
spoty/deezer_api.py
spoty/deezer_auth.py
spoty/deezer_auth_manualy.py
spoty/m3u8_playlist.py
spoty/spotify_api.py
spoty/utils.py
spoty/commands/__init__.py
spoty/commands/deezer_commands.py
spoty/commands/get_group.py
spoty/commands/get_second_group.py
spoty/commands/spotify_like_commands.py
spoty/commands/spotify_playlist_commands.py
spoty/commands/spotify_track_commands.py
spoty/commands/duplicates_commands/__init__.py
spoty/commands/duplicates_commands/add_missing_tags_command.py
spoty/commands/duplicates_commands/export_duplicates_command.py
spoty/commands/duplicates_commands/get_duplicates_group.py
spoty/commands/duplicates_commands/get_unique_group.py
spoty/commands/duplicates_commands/get_unique_second_group.py
spoty/commands/duplicates_commands/print_duplicates_command.py
spoty/commands/duplicates_commands/replace_tags_command.py
spoty/commands/first_list_commands/__init__.py
spoty/commands/first_list_commands/copy_command.py
spoty/commands/first_list_commands/count_command.py
spoty/commands/first_list_commands/create_m3u8_command.py
spoty/commands/first_list_commands/delete_command.py
spoty/commands/first_list_commands/export_command.py
spoty/commands/first_list_commands/filter_group.py
spoty/commands/first_list_commands/find_deezer_group.py
spoty/commands/first_list_commands/find_deezer_group2.py
spoty/commands/first_list_commands/find_duplicates_command.py
spoty/commands/first_list_commands/find_spotify_group.py
spoty/commands/first_list_commands/find_spotify_group2.py
spoty/commands/first_list_commands/import_deezer_command.py
spoty/commands/first_list_commands/import_spotify_command.py
spoty/commands/first_list_commands/move_command.py
spoty/commands/first_list_commands/print_command.py
spoty/commands/first_list_commands/sync_spotify_command.py
spoty/commands/second_list_commands/__init__.py
spoty/commands/second_list_commands/filter_second_group.py
spoty-0.1.11.dist-info/LICENSE
spoty-0.1.11.dist-info/METADATA
spoty-0.1.11.dist-info/WHEEL
spoty-0.1.11.dist-info/entry_points.txt
spoty-0.1.11.dist-info/top_level.txt
spoty-0.1.11.dist-info/RECORD
