Metadata-Version: 2.1
Name: spoty
Version: 0.1.11
Summary: CLI tool for management of Spotify, Deezer and other music services as well as local music files.
Home-page: https://github.com/dy-sh/spoty
Author: Dmitry Savosh
Author-email: d.savosh@gmail.com
License: MIT
Keywords: music,audio,spotify,deezer
Classifier: Development Status :: 3 - Alpha
Classifier: License :: OSI Approved :: MIT License
Classifier: Environment :: Console
Classifier: Topic :: Multimedia :: Sound/Audio
Classifier: Operating System :: OS Independent
Classifier: Programming Language :: Python :: 3
Requires-Python: >=3.7
License-File: LICENSE
Requires-Dist: click
Requires-Dist: deemix
Requires-Dist: deezersdk
Requires-Dist: dynaconf
Requires-Dist: Flask
Requires-Dist: loguru
Requires-Dist: mutagen
Requires-Dist: numpy
Requires-Dist: python-dateutil
Requires-Dist: spotipy
Requires-Dist: toml
